Metadata-Version: 2.1
Name: BracketFormatter
Version: 1.1.1
Summary: A custom logging formatter to use a [+] style log comment
Home-page: https://gitlab.com/Auctoris/bracketformatter
Author: AJ Poulter
Author-email: ajp@auctoris.co.uk
License: MIT
License-File: LICENSE
